dyn_rm/__init__.py
dyn_rm/dynamic_resource_manager.py
dyn_rm/hpc_system.py
dyn_rm/my_pmix.py
dyn_rm/my_pmix_constants.py
dyn_rm/plotter.py
dyn_rm/setup.py
dyn_rm/util.py
dyn_rm-1.0.6.dist-info/METADATA
dyn_rm-1.0.6.dist-info/WHEEL
dyn_rm-1.0.6.dist-info/entry_points.txt
dyn_rm-1.0.6.dist-info/top_level.txt
dyn_rm-1.0.6.dist-info/RECORD
