Metadata-Version: 2.1
Name: dyn-rm
Version: 1.0.6
Summary: A Dynamic Resource Manager for Dyn_PRRTE, Dyn_PMIx and Dyn_OMPI
Home-page: https://gitlab.inria.fr/dynres/dyn-procs/dyn_rm
Author: Dominik Huber
Author-email: domi.huber@tum.de
License: UNKNOWN
Platform: UNKNOWN
Requires-Dist: pypmix
